easymathlib-1.0.0.dist-info/licenses/LICENSE
mymathlib/__init__.py
mymathlib/advance_ops.py
mymathlib/basic_ops.py
mymathlib/geo_ops.py
easymathlib-1.0.0.dist-info/METADATA
easymathlib-1.0.0.dist-info/WHEEL
easymathlib-1.0.0.dist-info/top_level.txt
easymathlib-1.0.0.dist-info/RECORD
